{
  "generated_utc": "2026-07-13 16:07:10",
  "mode": "dry-run",
  "timeframe": "4h",
  "rule": "close > EMA(600) and RSI(84) > 50",
  "symbols": {
    "BTC/USDT": {
      "signal": "OUT",
      "in_position": false,
      "candle": "2026-07-13 12:00",
      "close": 62618.01,
      "ema": 68746.43688987,
      "rsi": 48.8,
      "ema_dist_pct": -8.91
    },
    "ETH/USDT": {
      "signal": "OUT",
      "in_position": false,
      "candle": "2026-07-13 12:00",
      "close": 1777.01,
      "ema": 1950.96211763,
      "rsi": 51.5,
      "ema_dist_pct": -8.92
    },
    "SOL/USDT": {
      "signal": "OUT",
      "in_position": false,
      "candle": "2026-07-13 12:00",
      "close": 75.81,
      "ema": 81.24875525,
      "rsi": 49.5,
      "ema_dist_pct": -6.69
    }
  }
}